pkg/__init__.py
vuln_utils-0.0.4.dist-info/METADATA
vuln_utils-0.0.4.dist-info/WHEEL
vuln_utils-0.0.4.dist-info/top_level.txt
vuln_utils-0.0.4.dist-info/RECORD
